metameq/__init__.py
metameq/_version.py
metameq/config/__init__.py
metameq/config/config.yml
metameq/config/standards.yml
metameq/src/__init__.py
metameq/src/__main__.py
metameq/src/metadata_configurator.py
metameq/src/metadata_extender.py
metameq/src/metadata_merger.py
metameq/src/metadata_transformers.py
metameq/src/metadata_validator.py
metameq/src/util.py
metameq/tests/__init__.py
metameq/tests/test_metadata_configurator.py
metameq/tests/test_metadata_extender.py
metameq/tests/test_metadata_merger.py
metameq/tests/test_metadata_transformers.py
metameq/tests/test_metadata_validator.py
metameq/tests/test_util.py
metameq/tests/data/invalid.yml
metameq/tests/data/test_config.yml
metameq-2026.1.2.dist-info/METADATA
metameq-2026.1.2.dist-info/WHEEL
metameq-2026.1.2.dist-info/entry_points.txt
metameq-2026.1.2.dist-info/top_level.txt
metameq-2026.1.2.dist-info/RECORD
