Metadata-Version: 2.4
Name: metameq
Version: 2026.1.2
Summary: Qiita-compliant metadata generation and validation tool
Home-page: https://github.com/AmandaBirmingham/metameq
Author: Amanda Birmingham
Author-email: abirmingham@ucsd.edu
License: BSD-3-Clause
Requires-Dist: click>=8.0.0
Requires-Dist: pandas>=1.3.0
Requires-Dist: PyYAML>=5.4.0
Requires-Dist: Cerberus>=1.3.4
Dynamic: author
Dynamic: author-email
Dynamic: description
Dynamic: home-page
Dynamic: license
Dynamic: requires-dist
Dynamic: summary
